cats/__init__.py
cats/errors.py
cats/identity.py
cats/identity.pyi
cats/plugins.py
cats/test_utils/__init__.py
cats/test_utils/client/__init__.py
cats/test_utils/client/connection.py
cats/test_utils/pytest/__init__.py
cats/test_utils/pytest/fixtures.py
cats/test_utils/pytest/plugin.py
cats/types.py
cats/utils.py
cats/v2/__init__.py
cats/v2/action.py
cats/v2/action.pyi
cats/v2/auth.py
cats/v2/client/__init__.py
cats/v2/client/__main__.py
cats/v2/client/connection.py
cats/v2/codecs.py
cats/v2/compression.py
cats/v2/config.py
cats/v2/connection.py
cats/v2/handshake.py
cats/v2/server/__init__.py
cats/v2/server/__main__.py
cats/v2/server/application.py
cats/v2/server/connection.py
cats/v2/server/handlers.py
cats/v2/server/handlers.pyi
cats/v2/server/middleware.py
cats/v2/server/proxy.py
cats/v2/server/server.py
cats/v2/statement.py
cats_python-4.7.0.dist-info/LICENSE
cats_python-4.7.0.dist-info/METADATA
cats_python-4.7.0.dist-info/WHEEL
cats_python-4.7.0.dist-info/entry_points.txt
cats_python-4.7.0.dist-info/RECORD
