Metadata-Version: 2.1
Name: cats-python
Version: 4.7.0
Summary: Cifrazia Action Transport System for Python
Home-page: https://adambrianbright.github.io/cats-python/
License: MIT
Keywords: cifrazia,tcp,rpc,cats,tornado
Author: Bogdan Parfenov
Author-email: adam.brian.bright@gmail.com
Requires-Python: >=3.12,<4.0
Classifier: Development Status :: 5 - Production/Stable
Classifier: Environment :: Console
Classifier: Framework :: AsyncIO
Classifier: Framework :: Pytest
Classifier: Intended Audience :: Developers
Classifier: License :: OSI Approved :: MIT License
Classifier: Natural Language :: English
Classifier: Natural Language :: Russian
Classifier: Operating System :: MacOS :: MacOS X
Classifier: Operating System :: Microsoft :: Windows :: Windows 10
Classifier: Operating System :: OS Independent
Classifier: Operating System :: POSIX :: Linux
Classifier: Programming Language :: Python :: 3
Classifier: Programming Language :: Python :: 3 :: Only
Classifier: Programming Language :: Python :: 3.10
Classifier: Topic :: Software Development
Classifier: Topic :: Software Development :: Libraries
Classifier: Typing :: Typed
Provides-Extra: django
Provides-Extra: pydantic
Requires-Dist: Django (>=4.0) ; extra == "django"
Requires-Dist: PyYAML (>=6.0,<7.0)
Requires-Dist: djangorestframework (>=3.13) ; extra == "django"
Requires-Dist: msgpack (>=1.0.3,<2.0.0)
Requires-Dist: pydantic (>=2.4.2) ; extra == "pydantic"
Requires-Dist: pytz (>=2023.3,<2024.0)
Requires-Dist: richerr (>=0.3.0,<0.4.0)
Requires-Dist: struct-model-python (>=0.2.0,<0.3.0)
Requires-Dist: toml (>=0.10.2,<0.11.0)
Requires-Dist: tornado (>=6.1,<7.0)
Requires-Dist: ujson (>=5.1.0,<6.0.0)
Project-URL: Bug Tracker, https://github.com/AdamBrianBright/cats-python/issues
Project-URL: ChangeLog, https://adambrianbright.github.io/cats-python/changelog
Project-URL: Contact Author, https://vk.com/adam_bright
Project-URL: Documentation, https://adambrianbright.github.io/cats-python/
Project-URL: Repository, https://github.com/AdamBrianBright/cats-python
